pytest_salt_runtests_bridge.py
pytest_salt_runtests_bridge-2019.12.5.dist-info/LICENSE
pytest_salt_runtests_bridge-2019.12.5.dist-info/METADATA
pytest_salt_runtests_bridge-2019.12.5.dist-info/WHEEL
pytest_salt_runtests_bridge-2019.12.5.dist-info/entry_points.txt
pytest_salt_runtests_bridge-2019.12.5.dist-info/top_level.txt
pytest_salt_runtests_bridge-2019.12.5.dist-info/RECORD
